{
    "UHC-202503082131-51d435d8": {
        "name": "omkar",
        "dob": "1111-11-11",
        "address": "hno 10-2/13 sangmeshwar colony beside nisty hospital gulbarga",
        "phone": "06361207771",
        "email": "omkarpadashetty123@gmail.com",
        "uin": "UIN-20250308-SCWA",
        "photo_path": "user_photos/UHC-202503082131-51d435d8.jpg",
        "qr_path": "qr_codes/UHC-202503082131-51d435d8.png",
        "created_at": "2025-03-08 21:31:48",
        "expiry_date": "2030-03-07"
    },
    "UHC-202503082138-8c9e2ad7": {
        "name": "OMKAR PADASHETTY",
        "dob": "2005-07-11",
        "address": "hno 10-2/13 sangmeshwar colony beside nisty hospital gulbarga",
        "phone": "8618075133",
        "email": "padashettyomkar11@gmail.com",
        "uin": "UIN-20250308-3652",
        "photo_path": "user_photos/UHC-202503082138-8c9e2ad7.jpg",
        "qr_path": "qr_codes/UHC-202503082138-8c9e2ad7.png",
        "created_at": "2025-03-08 21:38:32",
        "expiry_date": "2030-03-07",
        "verification_history": [
            {
                "timestamp": "2025-03-08 22:02:19",
                "method": "uin",
                "status": "success"
            }
        ]
    },
    "UHC-202503082155-53486049": {
        "name": "OMKAR PADASHETTY",
        "dob": "1111-11-11",
        "address": "hno 10-2/13 sangmeshwar colony beside nisty hospital gulbarga",
        "phone": "8618075133",
        "email": "padashettyomkar11@gmail.com",
        "uin": "UIN-20250308-I8AW",
        "photo_path": "user_photos/UHC-202503082155-53486049.jpg",
        "qr_path": "qr_codes/UHC-202503082155-53486049.png",
        "created_at": "2025-03-08 21:55:16",
        "expiry_date": "2030-03-07"
    },
    "UHC-202503082217-b5498725": {
        "name": "OMKAR P",
        "dob": "1111-11-11",
        "address": "hno 10-2/13 sangmeshwar colony beside nisty hospital gulbarga",
        "phone": "8618075133",
        "email": "padashettyomkar11@gmail.com",
        "uin": "UIN-20250308-C6CG",
        "photo_path": "user_photos/UHC-202503082217-b5498725.jpg",
        "qr_path": "qr_codes/UHC-202503082217-b5498725.png",
        "created_at": "2025-03-08 22:17:58",
        "expiry_date": "2030-03-07",
        "verification_history": [
            {
                "timestamp": "2025-03-08 22:18:11",
                "method": "uin",
                "status": "success"
            },
            {
                "timestamp": "2025-03-08 23:02:13",
                "method": "uin",
                "status": "success"
            }
        ]
    },
    "UHC-202503082240-4f98cf0c": {
        "name": "xz",
        "dob": "1111-11-11",
        "address": "xzxzx",
        "phone": "1234567890",
        "email": "omkarpadashetty123@gmail.com",
        "uin": "UIN-20250308-YS54",
        "photo_path": "user_photos\\UHC-202503082240-4f98cf0c.jpg",
        "qr_path": "qr_codes\\UHC-202503082240-4f98cf0c.png",
        "created_at": "2025-03-08 22:40:02",
        "expiry_date": "2030-03-07",
        "verification_history": [
            {
                "timestamp": "2025-03-08 22:40:29",
                "method": "uin",
                "status": "success"
            }
        ]
    },
    "UHC-202503082249-84312c4d": {
        "first_name": "avc",
        "last_name": "",
        "date_of_birth": "1245-03-12",
        "address": "anand hotel",
        "phone": "06361207771",
        "email": "padashettyomkar11@gmail.com",
        "uin": "UIN-20250308-NDEN",
        "photo_path": "user_photos/UHC-202503082249-84312c4d.jpg",
        "qr_path": "qr_codes/UHC-202503082249-84312c4d.png",
        "created_at": "2025-03-08 22:49:44",
        "expiry_date": "2030-03-07",
        "verification_history": [
            {
                "timestamp": "2025-03-08 22:50:02",
                "method": "uin",
                "status": "success"
            }
        ]
    },
    "UHC-202503082309-6161e07f": {
        "first_name": "123",
        "last_name": "",
        "date_of_birth": "12121-12-12",
        "address": "asds",
        "phone": "06361207771",
        "email": "padashettyomkar11@gmail.com",
        "uin": "UIN-20250308-9ZES",
        "photo_path": "user_photos/UHC-202503082309-6161e07f.jpg",
        "qr_path": "qr_codes/UHC-202503082309-6161e07f.png",
        "created_at": "2025-03-08 23:09:52",
        "expiry_date": "2030-03-07",
        "verification_history": [
            {
                "timestamp": "2025-03-08 23:10:07",
                "method": "uin",
                "status": "success"
            },
            {
                "timestamp": "2025-03-08 23:10:58",
                "method": "uin",
                "status": "success"
            }
        ]
    }
}